legos/__init__.py
legos/apod.py
legos.apod-0.1.2.dist-info/LICENSE
legos.apod-0.1.2.dist-info/METADATA
legos.apod-0.1.2.dist-info/WHEEL
legos.apod-0.1.2.dist-info/top_level.txt
legos.apod-0.1.2.dist-info/RECORD
