Metadata-Version: 2.1
Name: legos.apod
Version: 0.1.2
Summary: NASA Astonomy Photo of the Day fetcher plugin for Legobot
Home-page: https://github.com/drewpearce/legos.apod
Author: Drew Pearce
Author-email: drew@caffdev.com
License: UNKNOWN
Platform: UNKNOWN
Classifier: License :: OSI Approved :: GNU General Public License v2 (GPLv2)
Classifier: Programming Language :: Python :: 3
Classifier: Development Status :: 5 - Production/Stable
Requires-Python: >=3.6
Requires-Dist: legobot (<=2.0.0,>=1.3.6)
Requires-Dist: requests (==2.21.0)
